{"id":1222,"name":"IChannelArchiveDays","kind":256,"kindString":"Interface","flags":{},"children":[{"id":1223,"name":"dayList","kind":1024,"kindString":"Property","flags":{},"comment":{"summary":[{"kind":"text","text":"values by days"}]},"sources":[{"fileName":"src/analog/CommandBinaryBuffer.ts","fullFileName":"/home/stas/work/projects/jooby-dev/jooby-codec/src/analog/CommandBinaryBuffer.ts","line":66,"character":4,"url":"https://github.com/jooby-dev/jooby-codec/blob/03a5120/src/analog/CommandBinaryBuffer.ts#L66"}],"type":{"type":"array","elementType":{"type":"intrinsic","name":"number"}},"is":{"declaration":true},"location":{"query":"<internal>.Interface.IChannelArchiveDays","hash":"dayList"},"text":{"comment":"<p>values by days</p>\n"},"parentId":1222},{"id":1224,"name":"index","kind":1024,"kindString":"Property","flags":{"isInherited":true},"comment":{"summary":[{"kind":"text","text":"channel number"}]},"sources":[{"fileName":"src/analog/CommandBinaryBuffer.ts","fullFileName":"/home/stas/work/projects/jooby-dev/jooby-codec/src/analog/CommandBinaryBuffer.ts","line":29,"character":4,"url":"https://github.com/jooby-dev/jooby-codec/blob/03a5120/src/analog/CommandBinaryBuffer.ts#L29"}],"type":{"type":"intrinsic","name":"number"},"inheritedFrom":{"type":"reference","id":1285,"name":"IChannel.index"},"is":{"declaration":true},"location":{"query":"<internal>.Interface.IChannelArchiveDays","hash":"index"},"text":{"comment":"<p>channel number</p>\n"},"parentId":1222}],"groups":[{"title":"Properties","children":[1223,1224]}],"sources":[{"fileName":"src/analog/CommandBinaryBuffer.ts","fullFileName":"/home/stas/work/projects/jooby-dev/jooby-codec/src/analog/CommandBinaryBuffer.ts","line":64,"character":17,"url":"https://github.com/jooby-dev/jooby-codec/blob/03a5120/src/analog/CommandBinaryBuffer.ts#L64"}],"extendedTypes":[{"type":"reference","id":1284,"name":"IChannel"}],"is":{"declaration":true},"location":{"query":"<internal>.Interface.IChannelArchiveDays","hash":""},"text":{},"parentId":1059,"hierarchy":[{"name":"IChannel","linkId":"1284","children":[{"name":"IChannelArchiveDays","isTarget":true,"linkId":"1222"}]}]}
