{"id":953,"name":"fromBytes","kind":64,"kindString":"Function","flags":{},"children":[],"sources":[{"fileName":"src/analog/message.ts","fullFileName":"/home/stas/work/projects/jooby-dev/jooby-codec/src/analog/message.ts","line":102,"character":13,"url":"https://github.com/jooby-dev/jooby-codec/blob/03a5120/src/analog/message.ts#L102"}],"signatures":[{"id":954,"name":"fromBytes","kind":4096,"kindString":"Call signature","flags":{},"parameters":[{"id":955,"name":"data","kind":32768,"kindString":"Parameter","flags":{},"type":{"type":"reference","name":"Uint8Array","qualifiedName":"Uint8Array","package":"typescript"},"text":{}},{"id":956,"name":"direction","kind":32768,"kindString":"Parameter","flags":{},"type":{"type":"intrinsic","name":"number"},"defaultValue":"AUTO","text":{}},{"id":957,"name":"hardwareType","kind":32768,"kindString":"Parameter","flags":{"isOptional":true},"type":{"type":"intrinsic","name":"number"},"text":{}}],"type":{"type":"reference","id":1089,"name":"IMessage"},"is":{"declaration":false},"location":{"query":"analog.message.Function.fromBytes","hash":"fromBytes"},"text":{},"sources":[{"fileName":"src/analog/message.ts","fullFileName":"/home/stas/work/projects/jooby-dev/jooby-codec/src/analog/message.ts","line":102,"character":25,"url":"https://github.com/jooby-dev/jooby-codec/blob/03a5120/src/analog/message.ts#L102"}],"parentId":953}],"is":{"declaration":true},"location":{"query":"analog.message.Function.fromBytes","hash":""},"text":{},"parentId":948}
