{"id":2585,"name":"getHexFromBytes","kind":32,"kindString":"Variable","flags":{},"children":[],"sources":[{"fileName":"src/utils/getHexFromBytes.ts","fullFileName":"/home/stas/work/projects/jooby-dev/jooby-codec/src/utils/getHexFromBytes.ts","line":14,"character":0,"url":"https://github.com/jooby-dev/jooby-codec/blob/3200ba6/src/utils/getHexFromBytes.ts#L14"}],"type":{"type":"reflection","declaration":{"id":2586,"name":"getHexFromBytes","kind":65536,"kindString":"Type literal","flags":{},"sources":[{"fileName":"src/utils/getHexFromBytes.ts","line":14,"character":15,"url":"https://github.com/jooby-dev/jooby-codec/blob/3200ba6/src/utils/getHexFromBytes.ts#L14"}],"signatures":[{"id":2587,"name":"getHexFromBytes","kind":4096,"kindString":"Call signature","flags":{},"comment":{"summary":[{"kind":"text","text":"Convert byte array to hex string."}],"blockTags":[{"tag":"@example","content":[{"kind":"code","text":"```ts\ninput: [2, 5, 12, 255, 105, 139, 125]\noutput: '02 05 0c ff 69 8b 7d' or '0x02 0x05 0x0c 0xff 0x69 0x8b 0x7d'\n```"}]}]},"parameters":[{"id":2588,"name":"buffer","kind":32768,"kindString":"Parameter","flags":{},"comment":{"summary":[{"kind":"text","text":"input data to convert"}]},"type":{"type":"reference","name":"Uint8Array","qualifiedName":"Uint8Array","package":"typescript"},"text":{"comment":"<p>input data to convert</p>\n"}},{"id":2589,"name":"options","kind":32768,"kindString":"Parameter","flags":{},"comment":{"summary":[{"kind":"text","text":"formatting parameters"}]},"type":{"type":"reference","id":2604,"name":"IHexFormatOptions"},"defaultValue":"{}","text":{"comment":"<p>formatting parameters</p>\n"}}],"type":{"type":"intrinsic","name":"string"},"is":{"declaration":false},"location":{"query":"utils.getHexFromBytes.TypeLiteral.__type","hash":"__type"},"text":{"comment":"<p>Convert byte array to hex string.</p>\n<h5>Example:</h5><pre><code class=\"language-ts\"><span class=\"pl-en\">input</span>: [<span class=\"pl-c1\">2</span>, <span class=\"pl-c1\">5</span>, <span class=\"pl-c1\">12</span>, <span class=\"pl-c1\">255</span>, <span class=\"pl-c1\">105</span>, <span class=\"pl-c1\">139</span>, <span class=\"pl-c1\">125</span>]\n<span class=\"pl-en\">output</span>: <span class=\"pl-s\"><span class=\"pl-pds\">'</span>02 05 0c ff 69 8b 7d<span class=\"pl-pds\">'</span></span> <span class=\"pl-smi\">or</span> <span class=\"pl-s\"><span class=\"pl-pds\">'</span>0x02 0x05 0x0c 0xff 0x69 0x8b 0x7d<span class=\"pl-pds\">'</span></span>\n</code></pre>\n"},"sources":[{"fileName":"src/utils/getHexFromBytes.ts","fullFileName":"/home/stas/work/projects/jooby-dev/jooby-codec/src/utils/getHexFromBytes.ts","line":14,"character":15,"url":"https://github.com/jooby-dev/jooby-codec/blob/3200ba6/src/utils/getHexFromBytes.ts#L14"}],"parentId":2586}],"location":{"query":"utils.Variable.getHexFromBytes","hash":""}}},"is":{"declaration":true},"location":{"query":"utils.Variable.getHexFromBytes","hash":""},"text":{},"parentId":2580}
