{"id":2373,"name":"TTime2000","kind":4194304,"kindString":"Type alias","flags":{},"comment":{"summary":[{"kind":"text","text":"Seconds since year 2000."}],"blockTags":[{"tag":"@example","content":[{"kind":"text","text":"Time "},{"kind":"code","text":"`2023-04-03T14:01:17.000Z`"},{"kind":"text","text":" is "},{"kind":"code","text":"`1680530477`"},{"kind":"text","text":" in Unix time representation.\nUnix time for year "},{"kind":"code","text":"`2000`"},{"kind":"text","text":" is "},{"kind":"code","text":"`946684800`"},{"kind":"text","text":" so seconds since year "},{"kind":"code","text":"`2000`"},{"kind":"text","text":" is "},{"kind":"code","text":"`1680530477`"},{"kind":"text","text":" - "},{"kind":"code","text":"`946684800`"},{"kind":"text","text":" = "},{"kind":"code","text":"`733845677`"},{"kind":"text","text":"."}]}]},"children":[],"sources":[{"fileName":"src/utils/time.ts","fullFileName":"/home/stas/work/projects/jooby-dev/jooby-codec/src/utils/time.ts","line":15,"character":12,"url":"https://github.com/jooby-dev/jooby-codec/blob/3f668ea/src/utils/time.ts#L15"}],"type":{"type":"reference","id":2386,"typeArguments":[{"type":"intrinsic","name":"number"},{"type":"literal","value":"seconds"}],"name":"BrandType"},"is":{"declaration":true},"location":{"query":"utils.time.TypeAlias.TTime2000","hash":""},"text":{"comment":"<p>Seconds since year 2000.</p>\n<h5>Example:</h5><p>Time <code>2023-04-03T14:01:17.000Z</code> is <code>1680530477</code> in Unix time representation.\nUnix time for year <code>2000</code> is <code>946684800</code> so seconds since year <code>2000</code> is <code>1680530477</code> - <code>946684800</code> = <code>733845677</code>.</p>\n"},"parentId":2372}
