{"id":1296,"name":"IParameterActivationMethod","kind":256,"kindString":"Interface","flags":{},"comment":{"summary":[{"kind":"text","text":"Device activation method in LoRaWAN network.\ndeviceParameters.ACTIVATION_METHOD = "},{"kind":"code","text":"`9`"},{"kind":"text","text":"."}]},"children":[{"id":1297,"name":"type","kind":1024,"kindString":"Property","flags":{},"comment":{"summary":[{"kind":"code","text":"`0`"},{"kind":"text","text":" - OTAA, by default\n"},{"kind":"code","text":"`1`"},{"kind":"text","text":" - ABP"}],"blockTags":[{"tag":"@see","content":[{"kind":"text","text":"https://www.thethingsindustries.com/docs/devices/abp-vs-otaa/"}]}]},"sources":[{"fileName":"src/CommandBinaryBuffer.ts","fullFileName":"/home/stas/work/projects/jooby-dev/jooby-codec/src/CommandBinaryBuffer.ts","line":207,"character":4,"url":"https://github.com/jooby-dev/jooby-codec/blob/12ec02c/src/CommandBinaryBuffer.ts#L207"}],"type":{"type":"intrinsic","name":"number"},"is":{"declaration":true},"location":{"query":"<internal>.Interface.IParameterActivationMethod","hash":"type"},"text":{"comment":"<p><code>0</code> - OTAA, by default\n<code>1</code> - ABP</p>\n<h5>See:</h5><p><a href=\"https://www.thethingsindustries.com/docs/devices/abp-vs-otaa/\">https://www.thethingsindustries.com/docs/devices/abp-vs-otaa/</a></p>\n"},"parentId":1296}],"groups":[{"title":"Properties","children":[1297]}],"sources":[{"fileName":"src/CommandBinaryBuffer.ts","fullFileName":"/home/stas/work/projects/jooby-dev/jooby-codec/src/CommandBinaryBuffer.ts","line":200,"character":10,"url":"https://github.com/jooby-dev/jooby-codec/blob/12ec02c/src/CommandBinaryBuffer.ts#L200"}],"is":{"declaration":true},"location":{"query":"<internal>.Interface.IParameterActivationMethod","hash":""},"text":{"comment":"<p>Device activation method in LoRaWAN network.\ndeviceParameters.ACTIVATION_METHOD = <code>9</code>.</p>\n"},"parentId":1110,"hierarchy":[{"name":"IParameterActivationMethod","isTarget":true,"linkId":"1296"}]}
